pqdata/__init__.py
pqdata/_version.py
pqdata/core.py
pqdata/io/__init__.py
pqdata/io/read.py
pqdata/io/write.py
pqdata-0.1a1.dist-info/METADATA
pqdata-0.1a1.dist-info/WHEEL
pqdata-0.1a1.dist-info/licenses/LICENSE
pqdata-0.1a1.dist-info/RECORD
