Metadata-Version: 2.3
Name: pqdata
Version: 0.1a1
Summary: Parquet-based serialization for scverse
Project-URL: Documentation, https://gtca.github.io/pqdata
Project-URL: Source, https://github.com/gtca/pqdata
Project-URL: Home-page, https://github.com/gtca/pqdata
Author: Danila Bredikhin
Maintainer-email: Danila Bredikhin <danila@stanford.edu>
License-Expression: BSD-3-Clause
License-File: LICENSE
Classifier: Development Status :: 3 - Alpha
Classifier: Intended Audience :: Science/Research
Classifier: License :: OSI Approved :: BSD License
Classifier: Operating System :: OS Independent
Classifier: Programming Language :: Python :: 3
Classifier: Topic :: Scientific/Engineering :: Bio-Informatics
Requires-Python: >=3.10
Requires-Dist: pandas
Requires-Dist: pyarrow
Requires-Dist: scipy
Provides-Extra: dev
Requires-Dist: setuptools-scm; extra == 'dev'
Provides-Extra: doc
Requires-Dist: myst-parser; extra == 'doc'
Requires-Dist: nbsphinx; extra == 'doc'
Requires-Dist: pydata-sphinx-theme; extra == 'doc'
Requires-Dist: readthedocs-sphinx-search; extra == 'doc'
Requires-Dist: recommonmark; extra == 'doc'
Requires-Dist: sphinx; extra == 'doc'
Requires-Dist: sphinx-autodoc-typehints; extra == 'doc'
Requires-Dist: sphinx-automodapi; extra == 'doc'
Requires-Dist: sphinx-book-theme; extra == 'doc'
Requires-Dist: sphinxcontrib-bibtex; extra == 'doc'
Provides-Extra: test
Requires-Dist: anndata; extra == 'test'
Requires-Dist: mudata; extra == 'test'
Requires-Dist: pytest; extra == 'test'
Requires-Dist: pytest-cov; extra == 'test'
Requires-Dist: zarr; extra == 'test'
